{
  "id": 65,
  "name": "Sacramento Kings",
  "label": "kings",
  "is_defunct": false,
  "league_id": "nba",
  "chapters": [
    {
      "team_name": "Rochester Royals",
      "metro_id": "rochester",
      "label": "royals",
      "league_id": "nba",
      "start_year": 1948,
      "end_year": 1956
    },
    {
      "team_name": "Cincinnati Royals",
      "metro_id": "cincinnati",
      "label": "royals",
      "league_id": "nba",
      "start_year": 1957,
      "end_year": 1971
    },
    {
      "team_name": "Kansas City-Omaha Kings",
      "metro_id": "kansas-city",
      "league_id": "nba",
      "start_year": 1972,
      "end_year": 1974
    },
    {
      "team_name": "Kansas City Kings",
      "metro_id": "kansas-city",
      "league_id": "nba",
      "start_year": 1975,
      "end_year": 1984
    },
    {
      "team_name": "Sacramento Kings",
      "metro_id": "sacramento",
      "league_id": "nba",
      "start_year": 1985
    }
  ]
}