{
    "id": 83,
    "name": "1947-48 NHL Season",
    "start_year": 1947,
    "end_year": 1948,
    "league": "nhl",
    "total_major_divisions": 0,
    "total_minor_divisions": 0,
    "standings": {
        "results": [
            {"label": "maple-leafs", "wins": 32, "losses": 15, "ties": 13, "points": 77},
            {"label": "red-wings", "wins": 30, "losses": 18, "ties": 12, "points": 72},
            {"label": "bruins", "wins": 23, "losses": 24, "ties": 13, "points": 59},
            {"label": "rangers", "wins": 21, "losses": 26, "ties": 13, "points": 55},
            {"label": "canadiens", "wins": 20, "losses": 29, "ties": 11, "points": 51},
            {"label": "blackhawks", "wins": 20, "losses": 34, "ties": 6, "points": 46}
        ]
    },
    "postseason": {
        "rounds": [
            {
                "round_number": 1,
                "matchups": [
                    {
                        "winner": {
                            "label": "red-wings",
                            "games_won": 4
                        },
                        "loser": {
                            "label": "rangers",
                            "games_won": 2
                        }
                    },
                    {
                        "winner": {
                            "label": "maple-leafs",
                            "games_won": 4
                        },
                        "loser": {
                            "label": "bruins",
                            "games_won": 1
                        }
                    }
                ]
            },
            {
                "round_number": 2,
                "matchups": [
                    {
                        "winner": {
                            "label": "maple-leafs",
                            "games_won": 4
                        },
                        "loser": {
                            "label": "red-wings",
                            "games_won": 0
                        },
                        "is_championship_round": true
                    }
                ]
            }
        ]
    }
}